rfc_sdk/Account.py
rfc_sdk/Flow.py
rfc_sdk/__init__.py
rfc_sdk/utils/createApiCaller.py
rfc_sdk-0.0.1a2.dist-info/METADATA
rfc_sdk-0.0.1a2.dist-info/WHEEL
rfc_sdk-0.0.1a2.dist-info/RECORD
