Metadata-Version: 2.1
Name: rfc-sdk
Version: 0.0.1a2
Summary: 
Author: randomforest
Author-email: admin@randomforest.cloud
Requires-Python: >=3.12,<4.0
Classifier: Programming Language :: Python :: 3
Classifier: Programming Language :: Python :: 3.12
Requires-Dist: requests-toolbelt (>=1.0.0,<2.0.0)
